{
    "Entities": [
        {
            "Name": "person",
            "Fields": [
                {
                    "Name": "id",
                    "Type": "Primitive",
                    "PrimitiveType": "String"
                },
                {
                    "Name": "age",
                    "Type": "Primitive",
                    "PrimitiveType": "Int"
                },
                {
                    "Name": "name",
                    "Type": "Primitive",
                    "PrimitiveType": "String"
                }
            ]
        }
    ]
}